abx_pkg/__init__.py
abx_pkg/admin.py
abx_pkg/apps.py
abx_pkg/base_types.py
abx_pkg/binary.py
abx_pkg/binprovider.py
abx_pkg/binprovider_ansible.py
abx_pkg/binprovider_apt.py
abx_pkg/binprovider_brew.py
abx_pkg/binprovider_npm.py
abx_pkg/binprovider_pip.py
abx_pkg/binprovider_pyinfra.py
abx_pkg/models.py
abx_pkg/semver.py
abx_pkg/settings.py
abx_pkg/shallowbinary.py
abx_pkg/tests.py
abx_pkg/views.py
abx_pkg-0.6.0.dist-info/METADATA
abx_pkg-0.6.0.dist-info/WHEEL
abx_pkg-0.6.0.dist-info/licenses/LICENSE
abx_pkg-0.6.0.dist-info/RECORD
