Metadata-Version: 2.3
Name: abx-pkg
Version: 0.6.0
Summary: System package manager interfaces with Python type hints
Project-URL: Homepage, https://github.com/ArchiveBox/abx-pkg
Project-URL: Source, https://github.com/ArchiveBox/abx-pkg
Project-URL: Documentation, https://github.com/ArchiveBox/abx-pkg
Project-URL: Bug Tracker, https://github.com/ArchiveBox/abx-pkg/issues
Project-URL: Changelog, https://github.com/ArchiveBox/abx-pkg/releases
Project-URL: Donate, https://github.com/ArchiveBox/ArchiveBox/wiki/Donations
Author-email: Nick Sweeting <abx-pkg-pyproject-toml@sweeting.me>
License: MIT
Keywords: apt,brew,dependencies,packagemanager,pip,pydantic,system
Classifier: Environment :: Web Environment
Classifier: Framework :: Django
Classifier: Framework :: Django :: 4.0
Classifier: Framework :: Django :: 4.1
Classifier: Framework :: Django :: 4.2
Classifier: Framework :: Django :: 5.0
Classifier: Framework :: Django :: 5.1
Classifier: Intended Audience :: Developers
Classifier: Natural Language :: English
Classifier: Programming Language :: Python
Classifier: Programming Language :: Python :: 3
Classifier: Programming Language :: Python :: 3 :: Only
Classifier: Programming Language :: Python :: 3.10
Classifier: Programming Language :: Python :: 3.11
Classifier: Programming Language :: Python :: 3.12
Requires-Python: >=3.10
Requires-Dist: pip>=24.3.1
Requires-Dist: platformdirs>=4.3.6
Requires-Dist: pydantic-core>=2.18.2
Requires-Dist: pydantic>=2.7.1
Requires-Dist: typing-extensions>=4.11.0
Provides-Extra: all
Requires-Dist: ansible-core>=2.17.5; extra == 'all'
Requires-Dist: ansible-runner>=2.4.0; extra == 'all'
Requires-Dist: ansible>=10.5.0; extra == 'all'
Requires-Dist: pyinfra>=2.6.1; extra == 'all'
Provides-Extra: ansible
Requires-Dist: ansible-core>=2.17.5; extra == 'ansible'
Requires-Dist: ansible-runner>=2.4.0; extra == 'ansible'
Requires-Dist: ansible>=10.5.0; extra == 'ansible'
Provides-Extra: pyinfra
Requires-Dist: pyinfra>=2.6.1; extra == 'pyinfra'
